LICENSE.txt
MANIFEST.in
README.md
gdapi.py
requirements.txt
setup.py
gdapi_python.egg-info/PKG-INFO
gdapi_python.egg-info/SOURCES.txt
gdapi_python.egg-info/dependency_links.txt
gdapi_python.egg-info/entry_points.txt
gdapi_python.egg-info/requires.txt
gdapi_python.egg-info/top_level.txt