Metadata-Version: 1.0
Name: gdapi-python
Version: 0.2.1
Summary: Python API and CLI for GDAPI standard
Home-page: https://github.com/godaddy/gdapi-python
Author: Darren Shepherd
Author-email: darren.s.shepherd@gmail.com
License: MIT Style
Platform: UNKNOWN
